cbreaker/__init__.py
cbreaker/enums.py
cbreaker/exceptions.py
cbreaker/py.typed
cbreaker/core/__init__.py
cbreaker/core/breaker.py
cbreaker/core/states.py
cbreaker/decorators/__init__.py
cbreaker/decorators/circuit.py
cbreaker/detectors/__init__.py
cbreaker/detectors/base.py
cbreaker/detectors/combined.py
cbreaker/detectors/sliding_window.py
cbreaker/detectors/time_based.py
cbreaker/storage/__init__.py
cbreaker/storage/base.py
cbreaker/storage/memory.py
cbreaker/storage/redis_storage.py
c_breaker-0.1.6.dist-info/METADATA
c_breaker-0.1.6.dist-info/WHEEL
c_breaker-0.1.6.dist-info/RECORD
