Metadata-Version: 2.4
Name: c-breaker
Version: 0.1.6
Summary: A flexible circuit breaker library for Python with multiple failure detection strategies and Redis support
Project-URL: Homepage, https://github.com/500ping/c-breaker
Project-URL: Documentation, https://github.com/500ping/c-breaker#readme
Project-URL: Repository, https://github.com/500ping/c-breaker
Project-URL: Issues, https://github.com/500ping/c-breaker/issues
Author-email: 500ping <ndt512x@gmail.com>
License: MIT
Keywords: circuit-breaker,distributed-systems,fault-tolerance,microservices,resilience
Classifier: Development Status :: 4 - Beta
Classifier: Intended Audience :: Developers
Classifier: License :: OSI Approved :: MIT License
Classifier: Operating System :: OS Independent
Classifier: Programming Language :: Python :: 3
Classifier: Programming Language :: Python :: 3.12
Classifier: Programming Language :: Python :: 3.13
Classifier: Topic :: Software Development :: Libraries :: Python Modules
Classifier: Typing :: Typed
Requires-Python: >=3.12
Provides-Extra: all
Requires-Dist: redis>=5.0.0; extra == 'all'
Provides-Extra: redis
Requires-Dist: redis>=5.0.0; extra == 'redis'
